RandomUsers/Exceptions.py
RandomUsers/Fields.py
RandomUsers/Models.py
RandomUsers/__init__.py
RandomUsers/data.py
tests/__init__.py
tests/test_fields.py
tests/test_models.py
RandomUsers-1.3.dist-info/LICENSE
RandomUsers-1.3.dist-info/METADATA
RandomUsers-1.3.dist-info/WHEEL
RandomUsers-1.3.dist-info/top_level.txt
RandomUsers-1.3.dist-info/RECORD
