Metadata-Version: 2.1
Name: RandomUsers
Version: 1.3
Summary: A simple tool helps you generate fake data.
Home-page: https://github.com/SiriusKoan/RandomUsers
Author: SiriusKoan
Author-email: k.peihsun@gmail.com
License: MIT
Platform: UNKNOWN
Classifier: License :: OSI Approved :: MIT License
Classifier: Programming Language :: Python
Classifier: Programming Language :: Python :: 3
Classifier: Programming Language :: Python :: 3.7
License-File: LICENSE
